{
    "meta": {
        "last_updated_utc": "2026-06-05 11:29:02 UTC",
        "engine_run_status": "OPTIMIZED_STABLE"
    },
    "portfolio": [
        {
            "ticker": "INFY",
            "spot": 1199.0,
            "direction": "BEARISH",
            "contract": "1200 PE",
            "entry": 1199.0,
            "target": 1195.81,
            "stop_loss": 1200.59,
            "confidence": 57.49,
            "rsi": 51.29,
            "atr": 2.13
        },
        {
            "ticker": "MARUTI",
            "spot": 13050.0,
            "direction": "BULLISH",
            "contract": "13050 CE",
            "entry": 13050.0,
            "target": 13086.17,
            "stop_loss": 13031.92,
            "confidence": 56.04,
            "rsi": 41.65,
            "atr": 24.11
        },
        {
            "ticker": "RELIANCE",
            "spot": 1291.5,
            "direction": "BEARISH",
            "contract": "1300 PE",
            "entry": 1291.5,
            "target": 1288.72,
            "stop_loss": 1292.89,
            "confidence": 53.14,
            "rsi": 46.57,
            "atr": 1.85
        },
        {
            "ticker": "BHARTIARTL",
            "spot": 1796.0,
            "direction": "BULLISH",
            "contract": "1800 CE",
            "entry": 1796.0,
            "target": 1800.61,
            "stop_loss": 1793.69,
            "confidence": 53.14,
            "rsi": 44.86,
            "atr": 3.07
        },
        {
            "ticker": "ITC",
            "spot": 280.95,
            "direction": "BULLISH",
            "contract": "280 CE",
            "entry": 280.95,
            "target": 281.58,
            "stop_loss": 280.64,
            "confidence": 53.14,
            "rsi": 61.36,
            "atr": 0.42
        },
        {
            "ticker": "HDFCBANK",
            "spot": 748.0,
            "direction": "BULLISH",
            "contract": "750 CE",
            "entry": 748.0,
            "target": 750.09,
            "stop_loss": 746.96,
            "confidence": 52.17,
            "rsi": 51.51,
            "atr": 1.39
        },
        {
            "ticker": "SBIN",
            "spot": 977.0,
            "direction": "BULLISH",
            "contract": "980 CE",
            "entry": 977.0,
            "target": 979.91,
            "stop_loss": 975.54,
            "confidence": 51.21,
            "rsi": 47.63,
            "atr": 1.94
        },
        {
            "ticker": "TCS",
            "spot": 2196.0,
            "direction": "BULLISH",
            "contract": "2200 CE",
            "entry": 2196.0,
            "target": 2200.36,
            "stop_loss": 2193.82,
            "confidence": 50.24,
            "rsi": 31.84,
            "atr": 2.91
        },
        {
            "ticker": "ICICIBANK",
            "spot": 1260.3,
            "direction": "BULLISH",
            "contract": "1250 CE",
            "entry": 1260.3,
            "target": 1263.76,
            "stop_loss": 1258.57,
            "confidence": 40.1,
            "rsi": 48.59,
            "atr": 2.31
        }
    ]
}